{
  "updatedAt": "2026-04-08T14:30:23.283Z",
  "equityUsd": 11637.045032136395,
  "pnlUsd": 11537.045032,
  "pnlPct": 11537.045032,
  "solBalance": 30.11497304859557,
  "usdcBalance": 9096.446675778958,
  "netSolAccumulated": 30.11497304859557,
  "tradeCount": 66,
  "latestTrade": {
    "fillId": "cab0cc99-f848-4d29-b691-52eff1cb027e",
    "intentId": "dd1757ab-02c5-48d6-90fe-93cc85bb2073",
    "timestamp": "2026-04-08T13:50:16.722Z",
    "baseSymbol": "SOL",
    "quoteSymbol": "USDC",
    "notionalUsdRequested": 7.700000000000001,
    "notionalUsdExecuted": 7.700000000000001,
    "sizeSolExecuted": 0.091271921,
    "avgPriceUsd": 84.36329503791205,
    "slippageBpsSimulated": 50,
    "feesUsdSimulated": 0
  },
  "recommendations": []
}