{
  "updatedAt": "2026-04-11T00:21:24.358Z",
  "equityUsd": 11655.762396916354,
  "pnlUsd": 11555.762397,
  "pnlPct": 11555.762397,
  "solBalance": 33.10843844267219,
  "usdcBalance": 8852.185765778899,
  "netSolAccumulated": 33.10843844267219,
  "tradeCount": 149,
  "latestTrade": {
    "fillId": "b715d964-2352-4d68-b6b3-6cc23b1625c3",
    "intentId": "21682b7c-e727-4201-be1b-9f0ee2c1a2b7",
    "timestamp": "2026-04-11T00:21:24.353Z",
    "baseSymbol": "SOL",
    "quoteSymbol": "USDC",
    "notionalUsdRequested": 7.700000000000001,
    "notionalUsdExecuted": 7.700000000000001,
    "sizeSolExecuted": 0.090932052,
    "avgPriceUsd": 84.67861255347016,
    "slippageBpsSimulated": 50,
    "feesUsdSimulated": 0
  },
  "recommendations": []
}